mcp_server_obsidian_omnisearch/__init__.py
mcp_server_obsidian_omnisearch/__main__.py
mcp_server_obsidian_omnisearch/server.py
mcp_server_obsidian_omnisearch-0.1.2.dist-info/METADATA
mcp_server_obsidian_omnisearch-0.1.2.dist-info/WHEEL
mcp_server_obsidian_omnisearch-0.1.2.dist-info/entry_points.txt
mcp_server_obsidian_omnisearch-0.1.2.dist-info/licenses/LICENSE
mcp_server_obsidian_omnisearch-0.1.2.dist-info/RECORD
