Metadata-Version: 2.4
Name: mcp-server-obsidian-omnisearch
Version: 0.1.2
Summary: Add your description here
Author: anpigon
Maintainer-email: anpigon <anpigon@kakao.com>
License: MIT
License-File: LICENSE
Keywords: automation,http,llm,mcp,obsidian,omnisearch,second-brain
Classifier: Development Status :: 4 - Beta
Classifier: Intended Audience :: Developers
Classifier: License :: OSI Approved :: MIT License
Classifier: Programming Language :: Python :: 3
Classifier: Programming Language :: Python :: 3.10
Requires-Python: >=3.10
Requires-Dist: aiohttp>=3.11.9
Requires-Dist: asyncio>=3.4.3
Requires-Dist: fastmcp>=0.3.3
Requires-Dist: requests>=2.32.3
